interaktiv/__init__.py
interaktiv/aiclient/__init__.py
interaktiv/aiclient/client.py
interaktiv/aiclient/configure.zcml
interaktiv/aiclient/dependencies.zcml
interaktiv/aiclient/helper.py
interaktiv/aiclient/interfaces.py
interaktiv/aiclient/permissions.zcml
interaktiv/aiclient/profiles.zcml
interaktiv/aiclient/testing.py
interaktiv/aiclient/controlpanels/__init__.py
interaktiv/aiclient/controlpanels/client_settings.py
interaktiv/aiclient/controlpanels/configure.zcml
interaktiv/aiclient/locales/__init__.py
interaktiv/aiclient/locales/__main__.py
interaktiv/aiclient/locales/interaktiv.aiclient.pot
interaktiv/aiclient/locales/de/LC_MESSAGES/interaktiv.aiclient.mo
interaktiv/aiclient/locales/de/LC_MESSAGES/interaktiv.aiclient.po
interaktiv/aiclient/locales/en/LC_MESSAGES/interaktiv.aiclient.mo
interaktiv/aiclient/locales/en/LC_MESSAGES/interaktiv.aiclient.po
interaktiv/aiclient/profiles/default/browserlayer.xml
interaktiv/aiclient/profiles/default/controlpanel.xml
interaktiv/aiclient/profiles/default/metadata.xml
interaktiv/aiclient/profiles/default/rolemap.xml
interaktiv/aiclient/profiles/default/types.xml
interaktiv/aiclient/profiles/default/registry/main.xml
interaktiv/aiclient/profiles/uninstall/browserlayer.xml
interaktiv/aiclient/setuphandlers/__init__.py
interaktiv/aiclient/subscribers/__init__.py
interaktiv/aiclient/subscribers/aiclient.py
interaktiv/aiclient/subscribers/configure.zcml
interaktiv/aiclient/upgrades/__init__.py
interaktiv/aiclient/upgrades/configure.zcml
interaktiv/aiclient/vocabularies/__init__.py
interaktiv/aiclient/vocabularies/configure.zcml
interaktiv/aiclient/vocabularies/models.py
interaktiv_aiclient-1.0.0.dist-info/METADATA
interaktiv_aiclient-1.0.0.dist-info/WHEEL
interaktiv_aiclient-1.0.0.dist-info/entry_points.txt
interaktiv_aiclient-1.0.0.dist-info/licenses/LICENSE.md
interaktiv_aiclient-1.0.0.dist-info/RECORD
