Metadata-Version: 2.4
Name: interaktiv.aiclient
Version: 1.0.0
Summary: OpenRouter integration with Plone
Project-URL: Homepage, https://github.com/interaktivgmbh/interaktiv.aiclient
Project-URL: PyPI, https://pypi.org/project/interaktiv.aiclient
Project-URL: Source, https://github.com/interaktivgmbh/interaktiv.aiclient
Project-URL: Tracker, https://github.com/interaktivgmbh/interaktiv.aiclient/issues
Author-email: Interaktiv GmbH <info@interaktiv.de>
License-Expression: GPL-2.0-only
License-File: LICENSE.md
Keywords: AI,CMS,OpenRouter,Plone,Python
Classifier: Development Status :: 4 - Beta
Classifier: Environment :: Web Environment
Classifier: Framework :: Plone
Classifier: Framework :: Plone :: 6.0
Classifier: Framework :: Plone :: 6.1
Classifier: Framework :: Plone :: Addon
Classifier: License :: OSI Approved :: GNU General Public License v2 (GPLv2)
Classifier: Operating System :: OS Independent
Classifier: Programming Language :: Python
Classifier: Programming Language :: Python :: 3.10
Classifier: Programming Language :: Python :: 3.11
Classifier: Programming Language :: Python :: 3.12
Classifier: Programming Language :: Python :: 3.13
Requires-Python: <3.14,>=3.10
Requires-Dist: openai
Requires-Dist: plone-api
Requires-Dist: plone-restapi
Requires-Dist: products-cmfplone
Provides-Extra: release
Requires-Dist: zest-pocompile; extra == 'release'
Requires-Dist: zest-releaser[recommended]; extra == 'release'
Requires-Dist: zestreleaser-towncrier; extra == 'release'
Provides-Extra: test
Requires-Dist: horse-with-no-namespace; extra == 'test'
Requires-Dist: plone-app-testing; extra == 'test'
Requires-Dist: plone-restapi[test]; extra == 'test'
Requires-Dist: pytest; extra == 'test'
Requires-Dist: pytest-cov; extra == 'test'
Requires-Dist: pytest-plone>=0.5.0; extra == 'test'
